podaac/__init__.py
podaac/lambda_handler/__init__.py
podaac/lambda_handler/clean_lambda_handler.py
podaac/lambda_handler/cumulus_cli_handler/__init__.py
podaac/lambda_handler/cumulus_cli_handler/handlers.py
podaac/lambda_handler/lambda_handler.py
podaac/tig/__init__.py
podaac/tig/cli.py
podaac/tig/generate_hitide_config.py
podaac/tig/generate_thumbnails.sh
podaac/tig/tig.py
podaac_tig-0.13.1.dist-info/LICENSE
podaac_tig-0.13.1.dist-info/METADATA
podaac_tig-0.13.1.dist-info/WHEEL
podaac_tig-0.13.1.dist-info/entry_points.txt
podaac_tig-0.13.1.dist-info/RECORD
