Metadata-Version: 2.1
Name: podaac-tig
Version: 0.13.1
Summary: Tool for Image Generation (TIG)
Home-page: https://github.jpl.nasa.gov/podaac/tig
License: Apache-2.0
Author: podaac-tva
Author-email: podaac-tva@jpl.nasa.gov
Requires-Python: >=3.10,<3.13
Classifier: License :: OSI Approved :: Apache Software License
Classifier: Programming Language :: Python :: 3
Classifier: Programming Language :: Python :: 3.10
Classifier: Programming Language :: Python :: 3.11
Classifier: Programming Language :: Python :: 3.12
Classifier: Topic :: Software Development :: Libraries :: Python Modules
Requires-Dist: click (>=8.1.7,<9.0.0)
Requires-Dist: cumulus-process (>=1.4.0,<2.0.0)
Requires-Dist: imageio (>=2.34.0,<3.0.0)
Requires-Dist: matplotlib (>=3.8.3,<4.0.0)
Requires-Dist: netCDF4 (>=1.6.5,<2.0.0)
Requires-Dist: numpy (>=2.2.1,<3.0.0)
Requires-Dist: pygeogrids (>=0.5.0,<0.6.0)
Requires-Dist: requests (>=2.31.0,<3.0.0)
Requires-Dist: scipy (>=1.12.0,<2.0.0)
Requires-Dist: xarray (>=2025.1.1,<2026.0.0)
Project-URL: Repository, https://github.jpl.nasa.gov/podaac/tig
